vsutillib/vsxml/__init__.py
vsutillib/vsxml/xml.py
vsutillib/vsxml/classes/__init__.py
vsutillib/vsxml/classes/xmldb.py
vsutillib_vsxml-1.6.0.dist-info/AUTHORS
vsutillib_vsxml-1.6.0.dist-info/LICENSE.txt
vsutillib_vsxml-1.6.0.dist-info/METADATA
vsutillib_vsxml-1.6.0.dist-info/WHEEL
vsutillib_vsxml-1.6.0.dist-info/top_level.txt
vsutillib_vsxml-1.6.0.dist-info/RECORD
